midtrans_python_rest_sdk/__init__.py
midtrans_python_rest_sdk/api.py
midtrans_python_rest_sdk/cli.py
midtrans_python_rest_sdk/config.py
midtrans_python_rest_sdk/exceptions.py
midtrans_python_rest_sdk/midtrans_python_rest_sdk.py
midtrans_python_rest_sdk/midtrans_python_rest_sdkz.py
midtrans_python_rest_sdk/resource.py
midtrans_python_rest_sdk/schemas.py
midtrans_python_rest_sdk/transactions.py
midtrans_python_rest_sdk/util.py
midtrans_python_rest_sdk-0.1.9.dist-info/DESCRIPTION.rst
midtrans_python_rest_sdk-0.1.9.dist-info/METADATA
midtrans_python_rest_sdk-0.1.9.dist-info/RECORD
midtrans_python_rest_sdk-0.1.9.dist-info/WHEEL
midtrans_python_rest_sdk-0.1.9.dist-info/entry_points.txt
midtrans_python_rest_sdk-0.1.9.dist-info/metadata.json
midtrans_python_rest_sdk-0.1.9.dist-info/top_level.txt
