Metadata-Version: 2.0
Name: midtrans-python-rest-sdk
Version: 0.1.9
Summary: Midtrans Python REST SDK
Home-page: https://github.com/livingmine/midtrans_python_rest_sdk
Author: Muhammad Irfan
Author-email: irfan@rubyh.co
License: MIT license
Keywords: midtrans_python_rest_sdk
Platform: UNKNOWN
Classifier: Development Status :: 2 - Pre-Alpha
Classifier: Intended Audience :: Developers
Classifier: License :: OSI Approved :: MIT License
Classifier: Natural Language :: English
Classifier: Programming Language :: Python :: 2
Classifier: Programming Language :: Python :: 2.6
Classifier: Programming Language :: Python :: 2.7
Classifier: Programming Language :: Python :: 3
Classifier: Programming Language :: Python :: 3.3
Classifier: Programming Language :: Python :: 3.4
Classifier: Programming Language :: Python :: 3.5
Requires-Dist: Click (>=6.0)
Requires-Dist: marshmallow (>=1.0.0)
Requires-Dist: requests (>=1.0.0)
Requires-Dist: six (>=1.0.0)
